pyhf/__init__.py
pyhf/_version.py
pyhf/compat.py
pyhf/constraints.py
pyhf/events.py
pyhf/mixins.py
pyhf/patchset.py
pyhf/pdf.py
pyhf/probability.py
pyhf/readxml.py
pyhf/simplemodels.py
pyhf/typing.py
pyhf/utils.py
pyhf/workspace.py
pyhf/writexml.py
pyhf/cli/__init__.py
pyhf/cli/cli.py
pyhf/cli/complete.py
pyhf/cli/infer.py
pyhf/cli/patchset.py
pyhf/cli/rootio.py
pyhf/cli/spec.py
pyhf/contrib/__init__.py
pyhf/contrib/cli.py
pyhf/contrib/utils.py
pyhf/contrib/viz/__init__.py
pyhf/contrib/viz/brazil.py
pyhf/data/citation.bib
pyhf/exceptions/__init__.py
pyhf/infer/__init__.py
pyhf/infer/calculators.py
pyhf/infer/mle.py
pyhf/infer/test_statistics.py
pyhf/infer/utils.py
pyhf/infer/intervals/__init__.py
pyhf/infer/intervals/upper_limits.py
pyhf/interpolators/__init__.py
pyhf/interpolators/code0.py
pyhf/interpolators/code1.py
pyhf/interpolators/code2.py
pyhf/interpolators/code4.py
pyhf/interpolators/code4p.py
pyhf/modifiers/__init__.py
pyhf/modifiers/histosys.py
pyhf/modifiers/lumi.py
pyhf/modifiers/normfactor.py
pyhf/modifiers/normsys.py
pyhf/modifiers/shapefactor.py
pyhf/modifiers/shapesys.py
pyhf/modifiers/staterror.py
pyhf/optimize/__init__.py
pyhf/optimize/common.py
pyhf/optimize/mixins.py
pyhf/optimize/opt_jax.py
pyhf/optimize/opt_minuit.py
pyhf/optimize/opt_numpy.py
pyhf/optimize/opt_pytorch.py
pyhf/optimize/opt_scipy.py
pyhf/optimize/opt_tflow.py
pyhf/parameters/__init__.py
pyhf/parameters/paramsets.py
pyhf/parameters/paramview.py
pyhf/parameters/utils.py
pyhf/schema/__init__.py
pyhf/schema/loader.py
pyhf/schema/validator.py
pyhf/schema/variables.py
pyhf/schemas/HistFactorySchema.dtd
pyhf/schemas/1.0.0/defs.json
pyhf/schemas/1.0.0/jsonpatch.json
pyhf/schemas/1.0.0/measurement.json
pyhf/schemas/1.0.0/model.json
pyhf/schemas/1.0.0/patchset.json
pyhf/schemas/1.0.0/workspace.json
pyhf/tensor/__init__.py
pyhf/tensor/common.py
pyhf/tensor/jax_backend.py
pyhf/tensor/manager.py
pyhf/tensor/numpy_backend.py
pyhf/tensor/pytorch_backend.py
pyhf/tensor/tensorflow_backend.py
pyhf-0.7.5.dist-info/METADATA
pyhf-0.7.5.dist-info/WHEEL
pyhf-0.7.5.dist-info/entry_points.txt
pyhf-0.7.5.dist-info/licenses/AUTHORS
pyhf-0.7.5.dist-info/licenses/LICENSE
pyhf-0.7.5.dist-info/RECORD
