Metadata-Version: 2.1
Name: pyhf
Version: 0.7.5
Summary: pure-Python HistFactory implementation with tensors and autodiff
Project-URL: Documentation, https://pyhf.readthedocs.io/
Project-URL: Homepage, https://github.com/scikit-hep/pyhf
Project-URL: Issue Tracker, https://github.com/scikit-hep/pyhf/issues
Project-URL: Release Notes, https://pyhf.readthedocs.io/en/stable/release-notes.html
Project-URL: Releases, https://github.com/scikit-hep/pyhf/releases
Project-URL: Source Code, https://github.com/scikit-hep/pyhf
Author-email: Lukas Heinrich <lukas.heinrich@cern.ch>, Matthew Feickert <matthew.feickert@cern.ch>, Giordon Stark <gstark@cern.ch>
Maintainer-email: The Scikit-HEP admins <scikit-hep-admins@googlegroups.com>
License: Apache-2.0
License-File: AUTHORS
License-File: LICENSE
Keywords: fitting,jax,numpy,physics,pytorch,scipy,tensorflow
Classifier: Development Status :: 4 - Beta
Classifier: Environment :: WebAssembly :: Emscripten
Classifier: Intended Audience :: Science/Research
Classifier: License :: OSI Approved :: Apache Software License
Classifier: Programming Language :: Python :: 3
Classifier: Programming Language :: Python :: 3 :: Only
Classifier: Programming Language :: Python :: 3.7
Classifier: Programming Language :: Python :: 3.8
Classifier: Programming Language :: Python :: 3.9
Classifier: Programming Language :: Python :: 3.10
Classifier: Programming Language :: Python :: 3.11
Classifier: Programming Language :: Python :: Implementation :: CPython
Classifier: Topic :: Scientific/Engineering
Classifier: Topic :: Scientific/Engineering :: Physics
Requires-Python: >=3.7
Requires-Dist: click>=8.0.0
Requires-Dist: importlib-resources>=1.4.0; python_version < '3.9'
Requires-Dist: jsonpatch>=1.15
Requires-Dist: jsonschema>=4.15.0
Requires-Dist: numpy
Requires-Dist: pyyaml>=5.1
Requires-Dist: scipy>=1.2.0
Requires-Dist: tqdm>=4.56.0
Requires-Dist: typing-extensions>=3.7.4.3; python_version == '3.7'
Provides-Extra: all
Requires-Dist: pyhf[backends,contrib,shellcomplete,xmlio]; extra == 'all'
Provides-Extra: backends
Requires-Dist: pyhf[jax,minuit,tensorflow,torch]; extra == 'backends'
Provides-Extra: contrib
Requires-Dist: matplotlib>=3.0.0; extra == 'contrib'
Requires-Dist: requests>=2.22.0; extra == 'contrib'
Provides-Extra: develop
Requires-Dist: codemetapy>=2.3.0; extra == 'develop'
Requires-Dist: nox; extra == 'develop'
Requires-Dist: pre-commit; extra == 'develop'
Requires-Dist: pyhf[docs,test]; extra == 'develop'
Requires-Dist: tbump>=6.7.0; extra == 'develop'
Provides-Extra: docs
Requires-Dist: ipython!=8.7.0; extra == 'docs'
Requires-Dist: ipywidgets; extra == 'docs'
Requires-Dist: jupyterlite-pyodide-kernel>=0.0.7; extra == 'docs'
Requires-Dist: jupyterlite-sphinx>=0.8.0; extra == 'docs'
Requires-Dist: jupytext>=1.14.0; extra == 'docs'
Requires-Dist: nbsphinx!=0.8.8; extra == 'docs'
Requires-Dist: pyhf[contrib,xmlio]; extra == 'docs'
Requires-Dist: sphinx-click; extra == 'docs'
Requires-Dist: sphinx-copybutton!=0.5.1,>=0.3.2; extra == 'docs'
Requires-Dist: sphinx-issues; extra == 'docs'
Requires-Dist: sphinx-rtd-theme>=1.3.0; extra == 'docs'
Requires-Dist: sphinx>=7.0.0; extra == 'docs'
Requires-Dist: sphinxcontrib-bibtex~=2.1; extra == 'docs'
Provides-Extra: jax
Requires-Dist: jax>=0.2.10; extra == 'jax'
Requires-Dist: jaxlib!=0.1.68,>=0.1.61; extra == 'jax'
Provides-Extra: minuit
Requires-Dist: iminuit>=2.7.0; extra == 'minuit'
Provides-Extra: shellcomplete
Requires-Dist: click-completion; extra == 'shellcomplete'
Provides-Extra: tensorflow
Requires-Dist: tensorflow-macos>=2.7.0; platform_machine == 'arm64' and platform_system == 'Darwin' and extra == 'tensorflow'
Requires-Dist: tensorflow-probability!=0.20.0,>=0.11.0; extra == 'tensorflow'
Requires-Dist: tensorflow>=2.7.0; platform_machine != 'arm64' and extra == 'tensorflow'
Provides-Extra: test
Requires-Dist: graphviz; extra == 'test'
Requires-Dist: ipympl>=0.3.0; extra == 'test'
Requires-Dist: jupyter; extra == 'test'
Requires-Dist: papermill~=2.3.4; extra == 'test'
Requires-Dist: pydocstyle; extra == 'test'
Requires-Dist: pyhf[all]; extra == 'test'
Requires-Dist: pytest-benchmark[histogram]; extra == 'test'
Requires-Dist: pytest-console-scripts>=1.4.0; extra == 'test'
Requires-Dist: pytest-cov>=2.5.1; extra == 'test'
Requires-Dist: pytest-mock; extra == 'test'
Requires-Dist: pytest-mpl; extra == 'test'
Requires-Dist: pytest-socket>=0.2.0; extra == 'test'
Requires-Dist: pytest>=6.0; extra == 'test'
Requires-Dist: requests-mock>=1.9.0; extra == 'test'
Requires-Dist: scikit-hep-testdata>=0.4.11; extra == 'test'
Requires-Dist: scrapbook~=0.5.0; extra == 'test'
Provides-Extra: torch
Requires-Dist: torch>=1.10.0; extra == 'torch'
Provides-Extra: xmlio
Requires-Dist: uproot>=4.1.1; extra == 'xmlio'
